[
  {
    "payroll_month": "2024-08-01T00:00:00.000Z",
    "adviser_id": 3,
    "adviser_full_name": "Adam Deane",
    "ix_section": 0,
    "section": "Gross Income",
    "ix_category": 0,
    "category": "Commission Income",
    "ix_item": 0,
    "item": "Gross Commission Income",
    "amount": 4635.119999999999
  },
  {
    "payroll_month": "2024-08-01T00:00:00.000Z",
    "adviser_id": 3,
    "adviser_full_name": "Adam Deane",
    "ix_section": 0,
    "section": "Gross Income",
    "ix_category": 0,
    "category": "Commission Income",
    "ix_item": 1,
    "item": "GST",
    "amount": -382.71633027522967
  },
  {
    "payroll_month": "2024-08-01T00:00:00.000Z",
    "adviser_id": 3,
    "adviser_full_name": "Adam Deane",
    "ix_section": 0,
    "section": "Gross Income",
    "ix_category": 0,
    "category": "Commission Income",
    "ix_item": 2,
    "item": "Commission Income",
    "amount": 4252.403669724769
  },
  {
    "payroll_month": "2024-08-01T00:00:00.000Z",
    "adviser_id": 3,
    "adviser_full_name": "Adam Deane",
    "ix_section": 0,
    "section": "Gross Income",
    "ix_category": 1,
    "category": "Other Income",
    "ix_item": 0,
    "item": "Split Commission Income",
    "amount": 0
  },
  {
    "payroll_month": "2024-09-01T00:00:00.000Z",
    "adviser_id": 3,
    "adviser_full_name": "Adam Deane",
    "ix_section": 0,
    "section": "Gross Income",
    "ix_category": 1,
    "category": "Other Income",
    "ix_item": 2,
    "item": "TallRock Incentive",
    "amount": 4690.95
  },
  {
    "payroll_month": "2024-08-01T00:00:00.000Z",
    "adviser_id": 3,
    "adviser_full_name": "Adam Deane",
    "ix_section": 0,
    "section": "Gross Income",
    "ix_category": 2,
    "category": "Commission Expense",
    "ix_item": 0,
    "item": "TallRock Deduction",
    "amount": -1275.721100917431
  },
  {
    "payroll_month": "2024-08-01T00:00:00.000Z",
    "adviser_id": 3,
    "adviser_full_name": "Adam Deane",
    "ix_section": 0,
    "section": "Gross Income",
    "ix_category": 2,
    "category": "Commission Expense",
    "ix_item": 1,
    "item": "15% Clawback",
    "amount": 0
  },
  {
    "payroll_month": "2024-08-01T00:00:00.000Z",
    "adviser_id": 3,
    "adviser_full_name": "Adam Deane",
    "ix_section": 0,
    "section": "Gross Income",
    "ix_category": 2,
    "category": "Commission Expense",
    "ix_item": 2,
    "item": "BDM Commission Expense",
    "amount": 0
  },
  {
    "payroll_month": "2024-09-01T00:00:00.000Z",
    "adviser_id": 3,
    "adviser_full_name": "Adam Deane",
    "ix_section": 0,
    "section": "Gross Income",
    "ix_category": 2,
    "category": "Commission Expense",
    "ix_item": 3,
    "item": "Chauffeur",
    "amount": 750
  },
  {
    "payroll_month": "2024-10-01T00:00:00.000Z",
    "adviser_id": 3,
    "adviser_full_name": "Adam Deane",
    "ix_section": 0,
    "section": "Gross Income",
    "ix_category": 2,
    "category": "Commission Expense",
    "ix_item": 4,
    "item": "Chauffeur",
    "amount": 750
  },
  {
    "payroll_month": "2024-11-01T00:00:00.000Z",
    "adviser_id": 3,
    "adviser_full_name": "Adam Deane",
    "ix_section": 0,
    "section": "Gross Income",
    "ix_category": 2,
    "category": "Commission Expense",
    "ix_item": 5,
    "item": "Chauffeur",
    "amount": 750
  },
  {
    "payroll_month": "2024-12-01T00:00:00.000Z",
    "adviser_id": 3,
    "adviser_full_name": "Adam Deane",
    "ix_section": 0,
    "section": "Gross Income",
    "ix_category": 2,
    "category": "Commission Expense",
    "ix_item": 6,
    "item": "Chauffeur",
    "amount": 750
  },
  {
    "payroll_month": "2024-08-01T00:00:00.000Z",
    "adviser_id": 3,
    "adviser_full_name": "Adam Deane",
    "ix_section": 1,
    "section": "Net Income",
    "ix_category": 1,
    "category": "Other Expenses",
    "ix_item": 0,
    "item": "Split Commission Expense",
    "amount": 0
  },
  {
    "payroll_month": "2024-08-01T00:00:00.000Z",
    "adviser_id": 3,
    "adviser_full_name": "Adam Deane",
    "ix_section": 2,
    "section": "Payment Amount",
    "ix_category": 0,
    "category": "Other Deductions",
    "ix_item": 0,
    "item": "OW CPF Contribution",
    "amount": 0
  },
  {
    "payroll_month": "2024-08-01T00:00:00.000Z",
    "adviser_id": 3,
    "adviser_full_name": "Adam Deane",
    "ix_section": 2,
    "section": "Payment Amount",
    "ix_category": 1,
    "category": "Other Deductions",
    "ix_item": 1,
    "item": "AW CPF Contribution",
    "amount": 0
  },
  {
    "payroll_month": "2024-08-01T00:00:00.000Z",
    "adviser_id": 10,
    "adviser_full_name": "Craig French",
    "ix_section": 0,
    "section": "Gross Income",
    "ix_category": 0,
    "category": "Commission Income",
    "ix_item": 0,
    "item": "Gross Commission Income",
    "amount": 3450.08
  },
  {
    "payroll_month": "2024-08-01T00:00:00.000Z",
    "adviser_id": 10,
    "adviser_full_name": "Craig French",
    "ix_section": 0,
    "section": "Gross Income",
    "ix_category": 0,
    "category": "Commission Income",
    "ix_item": 1,
    "item": "GST",
    "amount": -284.8689908256883
  },
  {
    "payroll_month": "2024-08-01T00:00:00.000Z",
    "adviser_id": 10,
    "adviser_full_name": "Craig French",
    "ix_section": 0,
    "section": "Gross Income",
    "ix_category": 0,
    "category": "Commission Income",
    "ix_item": 2,
    "item": "Commission Income",
    "amount": 3165.2110091743116
  },
  {
    "payroll_month": "2024-08-01T00:00:00.000Z",
    "adviser_id": 10,
    "adviser_full_name": "Craig French",
    "ix_section": 0,
    "section": "Gross Income",
    "ix_category": 1,
    "category": "Other Income",
    "ix_item": 0,
    "item": "Split Commission Income",
    "amount": 0
  },
  {
    "payroll_month": "2024-08-01T00:00:00.000Z",
    "adviser_id": 10,
    "adviser_full_name": "Craig French",
    "ix_section": 0,
    "section": "Gross Income",
    "ix_category": 2,
    "category": "Commission Expense",
    "ix_item": 0,
    "item": "TallRock Deduction",
    "amount": -791.3027522935779
  },
  {
    "payroll_month": "2024-08-01T00:00:00.000Z",
    "adviser_id": 10,
    "adviser_full_name": "Craig French",
    "ix_section": 0,
    "section": "Gross Income",
    "ix_category": 2,
    "category": "Commission Expense",
    "ix_item": 1,
    "item": "15% Clawback",
    "amount": 0
  },
  {
    "payroll_month": "2024-08-01T00:00:00.000Z",
    "adviser_id": 10,
    "adviser_full_name": "Craig French",
    "ix_section": 0,
    "section": "Gross Income",
    "ix_category": 2,
    "category": "Commission Expense",
    "ix_item": 2,
    "item": "BDM Commission Expense",
    "amount": 0
  },
  {
    "payroll_month": "2024-08-01T00:00:00.000Z",
    "adviser_id": 10,
    "adviser_full_name": "Craig French",
    "ix_section": 1,
    "section": "Net Income",
    "ix_category": 1,
    "category": "Other Expenses",
    "ix_item": 0,
    "item": "Split Commission Expense",
    "amount": 0
  },
  {
    "payroll_month": "2024-08-01T00:00:00.000Z",
    "adviser_id": 10,
    "adviser_full_name": "Craig French",
    "ix_section": 2,
    "section": "Payment Amount",
    "ix_category": 0,
    "category": "Other Deductions",
    "ix_item": 0,
    "item": "OW CPF Contribution",
    "amount": 0
  },
  {
    "payroll_month": "2024-08-01T00:00:00.000Z",
    "adviser_id": 10,
    "adviser_full_name": "Craig French",
    "ix_section": 2,
    "section": "Payment Amount",
    "ix_category": 1,
    "category": "Other Deductions",
    "ix_item": 1,
    "item": "AW CPF Contribution",
    "amount": 0
  },
  {
    "payroll_month": "2024-08-01T00:00:00.000Z",
    "adviser_id": 2,
    "adviser_full_name": "Greg Etherstone",
    "ix_section": 0,
    "section": "Gross Income",
    "ix_category": 0,
    "category": "Commission Income",
    "ix_item": 0,
    "item": "Gross Commission Income",
    "amount": 1064.76
  },
  {
    "payroll_month": "2024-08-01T00:00:00.000Z",
    "adviser_id": 2,
    "adviser_full_name": "Greg Etherstone",
    "ix_section": 0,
    "section": "Gross Income",
    "ix_category": 0,
    "category": "Commission Income",
    "ix_item": 1,
    "item": "GST",
    "amount": -87.91596330275235
  },
  {
    "payroll_month": "2024-08-01T00:00:00.000Z",
    "adviser_id": 2,
    "adviser_full_name": "Greg Etherstone",
    "ix_section": 0,
    "section": "Gross Income",
    "ix_category": 0,
    "category": "Commission Income",
    "ix_item": 2,
    "item": "Commission Income",
    "amount": 976.8440366972477
  },
  {
    "payroll_month": "2024-08-01T00:00:00.000Z",
    "adviser_id": 2,
    "adviser_full_name": "Greg Etherstone",
    "ix_section": 0,
    "section": "Gross Income",
    "ix_category": 1,
    "category": "Other Income",
    "ix_item": 0,
    "item": "Split Commission Income",
    "amount": 64.74715596330276
  },
  {
    "payroll_month": "2024-08-01T00:00:00.000Z",
    "adviser_id": 2,
    "adviser_full_name": "Greg Etherstone",
    "ix_section": 0,
    "section": "Gross Income",
    "ix_category": 2,
    "category": "Commission Expense",
    "ix_item": 0,
    "item": "TallRock Deduction",
    "amount": 0
  },
  {
    "payroll_month": "2024-08-01T00:00:00.000Z",
    "adviser_id": 2,
    "adviser_full_name": "Greg Etherstone",
    "ix_section": 0,
    "section": "Gross Income",
    "ix_category": 2,
    "category": "Commission Expense",
    "ix_item": 1,
    "item": "15% Clawback",
    "amount": 0
  },
  {
    "payroll_month": "2024-08-01T00:00:00.000Z",
    "adviser_id": 2,
    "adviser_full_name": "Greg Etherstone",
    "ix_section": 0,
    "section": "Gross Income",
    "ix_category": 2,
    "category": "Commission Expense",
    "ix_item": 2,
    "item": "BDM Commission Expense",
    "amount": 0
  },
  {
    "payroll_month": "2024-08-01T00:00:00.000Z",
    "adviser_id": 2,
    "adviser_full_name": "Greg Etherstone",
    "ix_section": 1,
    "section": "Net Income",
    "ix_category": 1,
    "category": "Other Expenses",
    "ix_item": 0,
    "item": "Split Commission Expense",
    "amount": 0
  },
  {
    "payroll_month": "2024-08-01T00:00:00.000Z",
    "adviser_id": 2,
    "adviser_full_name": "Greg Etherstone",
    "ix_section": 2,
    "section": "Payment Amount",
    "ix_category": 0,
    "category": "Other Deductions",
    "ix_item": 0,
    "item": "OW CPF Contribution",
    "amount": 0
  },
  {
    "payroll_month": "2024-08-01T00:00:00.000Z",
    "adviser_id": 2,
    "adviser_full_name": "Greg Etherstone",
    "ix_section": 2,
    "section": "Payment Amount",
    "ix_category": 1,
    "category": "Other Deductions",
    "ix_item": 1,
    "item": "AW CPF Contribution",
    "amount": 0
  },
  {
    "payroll_month": "2024-08-01T00:00:00.000Z",
    "adviser_id": 17,
    "adviser_full_name": "Ian Black",
    "ix_section": 0,
    "section": "Gross Income",
    "ix_category": 0,
    "category": "Commission Income",
    "ix_item": 0,
    "item": "Gross Commission Income",
    "amount": 324.83
  },
  {
    "payroll_month": "2024-08-01T00:00:00.000Z",
    "adviser_id": 17,
    "adviser_full_name": "Ian Black",
    "ix_section": 0,
    "section": "Gross Income",
    "ix_category": 0,
    "category": "Commission Income",
    "ix_item": 1,
    "item": "GST",
    "amount": -26.820825688073413
  },
  {
    "payroll_month": "2024-08-01T00:00:00.000Z",
    "adviser_id": 17,
    "adviser_full_name": "Ian Black",
    "ix_section": 0,
    "section": "Gross Income",
    "ix_category": 0,
    "category": "Commission Income",
    "ix_item": 2,
    "item": "Commission Income",
    "amount": 298.0091743119266
  },
  {
    "payroll_month": "2024-08-01T00:00:00.000Z",
    "adviser_id": 17,
    "adviser_full_name": "Ian Black",
    "ix_section": 0,
    "section": "Gross Income",
    "ix_category": 1,
    "category": "Other Income",
    "ix_item": 0,
    "item": "Split Commission Income",
    "amount": 0
  },
  {
    "payroll_month": "2024-08-01T00:00:00.000Z",
    "adviser_id": 17,
    "adviser_full_name": "Ian Black",
    "ix_section": 0,
    "section": "Gross Income",
    "ix_category": 2,
    "category": "Commission Expense",
    "ix_item": 0,
    "item": "TallRock Deduction",
    "amount": -104.3032110091743
  },
  {
    "payroll_month": "2024-08-01T00:00:00.000Z",
    "adviser_id": 17,
    "adviser_full_name": "Ian Black",
    "ix_section": 0,
    "section": "Gross Income",
    "ix_category": 2,
    "category": "Commission Expense",
    "ix_item": 1,
    "item": "15% Clawback",
    "amount": 0
  },
  {
    "payroll_month": "2024-08-01T00:00:00.000Z",
    "adviser_id": 17,
    "adviser_full_name": "Ian Black",
    "ix_section": 0,
    "section": "Gross Income",
    "ix_category": 2,
    "category": "Commission Expense",
    "ix_item": 2,
    "item": "BDM Commission Expense",
    "amount": 0
  },
  {
    "payroll_month": "2024-08-01T00:00:00.000Z",
    "adviser_id": 17,
    "adviser_full_name": "Ian Black",
    "ix_section": 1,
    "section": "Net Income",
    "ix_category": 1,
    "category": "Other Expenses",
    "ix_item": 0,
    "item": "Split Commission Expense",
    "amount": 0
  },
  {
    "payroll_month": "2024-08-01T00:00:00.000Z",
    "adviser_id": 17,
    "adviser_full_name": "Ian Black",
    "ix_section": 2,
    "section": "Payment Amount",
    "ix_category": 0,
    "category": "Other Deductions",
    "ix_item": 0,
    "item": "OW CPF Contribution",
    "amount": 0
  },
  {
    "payroll_month": "2024-08-01T00:00:00.000Z",
    "adviser_id": 17,
    "adviser_full_name": "Ian Black",
    "ix_section": 2,
    "section": "Payment Amount",
    "ix_category": 1,
    "category": "Other Deductions",
    "ix_item": 1,
    "item": "AW CPF Contribution",
    "amount": 0
  },
  {
    "payroll_month": "2024-08-01T00:00:00.000Z",
    "adviser_id": 6,
    "adviser_full_name": "Jack Kwong",
    "ix_section": 0,
    "section": "Gross Income",
    "ix_category": 0,
    "category": "Commission Income",
    "ix_item": 0,
    "item": "Gross Commission Income",
    "amount": 478.71999999999997
  },
  {
    "payroll_month": "2024-08-01T00:00:00.000Z",
    "adviser_id": 6,
    "adviser_full_name": "Jack Kwong",
    "ix_section": 0,
    "section": "Gross Income",
    "ix_category": 0,
    "category": "Commission Income",
    "ix_item": 1,
    "item": "GST",
    "amount": -39.527339449541316
  },
  {
    "payroll_month": "2024-08-01T00:00:00.000Z",
    "adviser_id": 6,
    "adviser_full_name": "Jack Kwong",
    "ix_section": 0,
    "section": "Gross Income",
    "ix_category": 0,
    "category": "Commission Income",
    "ix_item": 2,
    "item": "Commission Income",
    "amount": 439.19266055045864
  },
  {
    "payroll_month": "2024-08-01T00:00:00.000Z",
    "adviser_id": 6,
    "adviser_full_name": "Jack Kwong",
    "ix_section": 0,
    "section": "Gross Income",
    "ix_category": 1,
    "category": "Other Income",
    "ix_item": 0,
    "item": "Split Commission Income",
    "amount": 0
  },
  {
    "payroll_month": "2024-08-01T00:00:00.000Z",
    "adviser_id": 6,
    "adviser_full_name": "Jack Kwong",
    "ix_section": 0,
    "section": "Gross Income",
    "ix_category": 2,
    "category": "Commission Expense",
    "ix_item": 0,
    "item": "TallRock Deduction",
    "amount": -153.71743119266054
  },
  {
    "payroll_month": "2024-08-01T00:00:00.000Z",
    "adviser_id": 6,
    "adviser_full_name": "Jack Kwong",
    "ix_section": 0,
    "section": "Gross Income",
    "ix_category": 2,
    "category": "Commission Expense",
    "ix_item": 1,
    "item": "15% Clawback",
    "amount": 0
  },
  {
    "payroll_month": "2024-08-01T00:00:00.000Z",
    "adviser_id": 6,
    "adviser_full_name": "Jack Kwong",
    "ix_section": 0,
    "section": "Gross Income",
    "ix_category": 2,
    "category": "Commission Expense",
    "ix_item": 2,
    "item": "BDM Commission Expense",
    "amount": 0
  },
  {
    "payroll_month": "2024-09-01T00:00:00.000Z",
    "adviser_id": 6,
    "adviser_full_name": "Jack Kwong",
    "ix_section": 0,
    "section": "Gross Income",
    "ix_category": 2,
    "category": "Commission Expense",
    "ix_item": 3,
    "item": "Chauffeur",
    "amount": 600
  },
  {
    "payroll_month": "2024-10-01T00:00:00.000Z",
    "adviser_id": 6,
    "adviser_full_name": "Jack Kwong",
    "ix_section": 0,
    "section": "Gross Income",
    "ix_category": 2,
    "category": "Commission Expense",
    "ix_item": 4,
    "item": "Chauffeur",
    "amount": 600
  },
  {
    "payroll_month": "2024-11-01T00:00:00.000Z",
    "adviser_id": 6,
    "adviser_full_name": "Jack Kwong",
    "ix_section": 0,
    "section": "Gross Income",
    "ix_category": 2,
    "category": "Commission Expense",
    "ix_item": 5,
    "item": "Chauffeur",
    "amount": 600
  },
  {
    "payroll_month": "2024-12-01T00:00:00.000Z",
    "adviser_id": 6,
    "adviser_full_name": "Jack Kwong",
    "ix_section": 0,
    "section": "Gross Income",
    "ix_category": 2,
    "category": "Commission Expense",
    "ix_item": 6,
    "item": "Chauffeur",
    "amount": 600
  },
  {
    "payroll_month": "2025-01-01T00:00:00.000Z",
    "adviser_id": 6,
    "adviser_full_name": "Jack Kwong",
    "ix_section": 0,
    "section": "Gross Income",
    "ix_category": 2,
    "category": "Commission Expense",
    "ix_item": 7,
    "item": "Chauffeur",
    "amount": 600
  },
  {
    "payroll_month": "2025-02-01T00:00:00.000Z",
    "adviser_id": 6,
    "adviser_full_name": "Jack Kwong",
    "ix_section": 0,
    "section": "Gross Income",
    "ix_category": 2,
    "category": "Commission Expense",
    "ix_item": 8,
    "item": "Chauffeur",
    "amount": 600
  },
  {
    "payroll_month": "2025-03-01T00:00:00.000Z",
    "adviser_id": 6,
    "adviser_full_name": "Jack Kwong",
    "ix_section": 0,
    "section": "Gross Income",
    "ix_category": 2,
    "category": "Commission Expense",
    "ix_item": 9,
    "item": "Chauffeur",
    "amount": 600
  },
  {
    "payroll_month": "2025-04-01T00:00:00.000Z",
    "adviser_id": 6,
    "adviser_full_name": "Jack Kwong",
    "ix_section": 0,
    "section": "Gross Income",
    "ix_category": 2,
    "category": "Commission Expense",
    "ix_item": 10,
    "item": "Chauffeur",
    "amount": 600
  },
  {
    "payroll_month": "2025-05-01T00:00:00.000Z",
    "adviser_id": 6,
    "adviser_full_name": "Jack Kwong",
    "ix_section": 0,
    "section": "Gross Income",
    "ix_category": 2,
    "category": "Commission Expense",
    "ix_item": 11,
    "item": "Chauffeur",
    "amount": 600
  },
  {
    "payroll_month": "2025-06-01T00:00:00.000Z",
    "adviser_id": 6,
    "adviser_full_name": "Jack Kwong",
    "ix_section": 0,
    "section": "Gross Income",
    "ix_category": 2,
    "category": "Commission Expense",
    "ix_item": 12,
    "item": "Chauffeur",
    "amount": 600
  },
  {
    "payroll_month": "2025-07-01T00:00:00.000Z",
    "adviser_id": 6,
    "adviser_full_name": "Jack Kwong",
    "ix_section": 0,
    "section": "Gross Income",
    "ix_category": 2,
    "category": "Commission Expense",
    "ix_item": 13,
    "item": "Chauffeur",
    "amount": 600
  },
  {
    "payroll_month": "2025-08-01T00:00:00.000Z",
    "adviser_id": 6,
    "adviser_full_name": "Jack Kwong",
    "ix_section": 0,
    "section": "Gross Income",
    "ix_category": 2,
    "category": "Commission Expense",
    "ix_item": 14,
    "item": "Chauffeur",
    "amount": 600
  },
  {
    "payroll_month": "2025-09-01T00:00:00.000Z",
    "adviser_id": 6,
    "adviser_full_name": "Jack Kwong",
    "ix_section": 0,
    "section": "Gross Income",
    "ix_category": 2,
    "category": "Commission Expense",
    "ix_item": 15,
    "item": "Chauffeur",
    "amount": 600
  },
  {
    "payroll_month": "2025-10-01T00:00:00.000Z",
    "adviser_id": 6,
    "adviser_full_name": "Jack Kwong",
    "ix_section": 0,
    "section": "Gross Income",
    "ix_category": 2,
    "category": "Commission Expense",
    "ix_item": 16,
    "item": "Chauffeur",
    "amount": 600
  },
  {
    "payroll_month": "2025-11-01T00:00:00.000Z",
    "adviser_id": 6,
    "adviser_full_name": "Jack Kwong",
    "ix_section": 0,
    "section": "Gross Income",
    "ix_category": 2,
    "category": "Commission Expense",
    "ix_item": 17,
    "item": "Chauffeur",
    "amount": 600
  },
  {
    "payroll_month": "2025-12-01T00:00:00.000Z",
    "adviser_id": 6,
    "adviser_full_name": "Jack Kwong",
    "ix_section": 0,
    "section": "Gross Income",
    "ix_category": 2,
    "category": "Commission Expense",
    "ix_item": 18,
    "item": "Chauffeur",
    "amount": 600
  },
  {
    "payroll_month": "2024-08-01T00:00:00.000Z",
    "adviser_id": 6,
    "adviser_full_name": "Jack Kwong",
    "ix_section": 1,
    "section": "Net Income",
    "ix_category": 1,
    "category": "Other Expenses",
    "ix_item": 0,
    "item": "Split Commission Expense",
    "amount": 0
  },
  {
    "payroll_month": "2024-08-01T00:00:00.000Z",
    "adviser_id": 6,
    "adviser_full_name": "Jack Kwong",
    "ix_section": 2,
    "section": "Payment Amount",
    "ix_category": 0,
    "category": "Other Deductions",
    "ix_item": 0,
    "item": "OW CPF Contribution",
    "amount": 0
  },
  {
    "payroll_month": "2024-08-01T00:00:00.000Z",
    "adviser_id": 6,
    "adviser_full_name": "Jack Kwong",
    "ix_section": 2,
    "section": "Payment Amount",
    "ix_category": 1,
    "category": "Other Deductions",
    "ix_item": 1,
    "item": "AW CPF Contribution",
    "amount": 0
  },
  {
    "payroll_month": "2024-08-01T00:00:00.000Z",
    "adviser_id": 5,
    "adviser_full_name": "Jarrod Wong",
    "ix_section": 0,
    "section": "Gross Income",
    "ix_category": 0,
    "category": "Commission Income",
    "ix_item": 0,
    "item": "Gross Commission Income",
    "amount": 1641.5400000000002
  },
  {
    "payroll_month": "2024-08-01T00:00:00.000Z",
    "adviser_id": 5,
    "adviser_full_name": "Jarrod Wong",
    "ix_section": 0,
    "section": "Gross Income",
    "ix_category": 0,
    "category": "Commission Income",
    "ix_item": 1,
    "item": "GST",
    "amount": -135.5400000000001
  },
  {
    "payroll_month": "2024-08-01T00:00:00.000Z",
    "adviser_id": 5,
    "adviser_full_name": "Jarrod Wong",
    "ix_section": 0,
    "section": "Gross Income",
    "ix_category": 0,
    "category": "Commission Income",
    "ix_item": 2,
    "item": "Commission Income",
    "amount": 1506
  },
  {
    "payroll_month": "2024-08-01T00:00:00.000Z",
    "adviser_id": 5,
    "adviser_full_name": "Jarrod Wong",
    "ix_section": 0,
    "section": "Gross Income",
    "ix_category": 1,
    "category": "Other Income",
    "ix_item": 0,
    "item": "Split Commission Income",
    "amount": 0
  },
  {
    "payroll_month": "2024-08-01T00:00:00.000Z",
    "adviser_id": 5,
    "adviser_full_name": "Jarrod Wong",
    "ix_section": 0,
    "section": "Gross Income",
    "ix_category": 2,
    "category": "Commission Expense",
    "ix_item": 0,
    "item": "TallRock Deduction",
    "amount": -527.1
  },
  {
    "payroll_month": "2024-08-01T00:00:00.000Z",
    "adviser_id": 5,
    "adviser_full_name": "Jarrod Wong",
    "ix_section": 0,
    "section": "Gross Income",
    "ix_category": 2,
    "category": "Commission Expense",
    "ix_item": 1,
    "item": "15% Clawback",
    "amount": 0
  },
  {
    "payroll_month": "2024-08-01T00:00:00.000Z",
    "adviser_id": 5,
    "adviser_full_name": "Jarrod Wong",
    "ix_section": 0,
    "section": "Gross Income",
    "ix_category": 2,
    "category": "Commission Expense",
    "ix_item": 2,
    "item": "BDM Commission Expense",
    "amount": 0
  },
  {
    "payroll_month": "2024-09-01T00:00:00.000Z",
    "adviser_id": 5,
    "adviser_full_name": "Jarrod Wong",
    "ix_section": 0,
    "section": "Gross Income",
    "ix_category": 2,
    "category": "Commission Expense",
    "ix_item": 3,
    "item": "Chauffeur",
    "amount": 750
  },
  {
    "payroll_month": "2024-09-01T00:00:00.000Z",
    "adviser_id": 5,
    "adviser_full_name": "Jarrod Wong",
    "ix_section": 0,
    "section": "Gross Income",
    "ix_category": 2,
    "category": "Commission Expense",
    "ix_item": 4,
    "item": "Chauffeur",
    "amount": 750
  },
  {
    "payroll_month": "2024-10-01T00:00:00.000Z",
    "adviser_id": 5,
    "adviser_full_name": "Jarrod Wong",
    "ix_section": 0,
    "section": "Gross Income",
    "ix_category": 2,
    "category": "Commission Expense",
    "ix_item": 5,
    "item": "Chauffeur",
    "amount": 750
  },
  {
    "payroll_month": "2024-10-01T00:00:00.000Z",
    "adviser_id": 5,
    "adviser_full_name": "Jarrod Wong",
    "ix_section": 0,
    "section": "Gross Income",
    "ix_category": 2,
    "category": "Commission Expense",
    "ix_item": 6,
    "item": "Chauffeur",
    "amount": 750
  },
  {
    "payroll_month": "2024-11-01T00:00:00.000Z",
    "adviser_id": 5,
    "adviser_full_name": "Jarrod Wong",
    "ix_section": 0,
    "section": "Gross Income",
    "ix_category": 2,
    "category": "Commission Expense",
    "ix_item": 7,
    "item": "Chauffeur",
    "amount": 750
  },
  {
    "payroll_month": "2024-11-01T00:00:00.000Z",
    "adviser_id": 5,
    "adviser_full_name": "Jarrod Wong",
    "ix_section": 0,
    "section": "Gross Income",
    "ix_category": 2,
    "category": "Commission Expense",
    "ix_item": 8,
    "item": "Chauffeur",
    "amount": 750
  },
  {
    "payroll_month": "2024-12-01T00:00:00.000Z",
    "adviser_id": 5,
    "adviser_full_name": "Jarrod Wong",
    "ix_section": 0,
    "section": "Gross Income",
    "ix_category": 2,
    "category": "Commission Expense",
    "ix_item": 9,
    "item": "Chauffeur",
    "amount": 750
  },
  {
    "payroll_month": "2024-12-01T00:00:00.000Z",
    "adviser_id": 5,
    "adviser_full_name": "Jarrod Wong",
    "ix_section": 0,
    "section": "Gross Income",
    "ix_category": 2,
    "category": "Commission Expense",
    "ix_item": 10,
    "item": "Chauffeur",
    "amount": 750
  },
  {
    "payroll_month": "2024-08-01T00:00:00.000Z",
    "adviser_id": 5,
    "adviser_full_name": "Jarrod Wong",
    "ix_section": 1,
    "section": "Net Income",
    "ix_category": 1,
    "category": "Other Expenses",
    "ix_item": 0,
    "item": "Split Commission Expense",
    "amount": 0
  },
  {
    "payroll_month": "2024-08-01T00:00:00.000Z",
    "adviser_id": 5,
    "adviser_full_name": "Jarrod Wong",
    "ix_section": 2,
    "section": "Payment Amount",
    "ix_category": 0,
    "category": "Other Deductions",
    "ix_item": 0,
    "item": "OW CPF Contribution",
    "amount": 0
  },
  {
    "payroll_month": "2024-08-01T00:00:00.000Z",
    "adviser_id": 5,
    "adviser_full_name": "Jarrod Wong",
    "ix_section": 2,
    "section": "Payment Amount",
    "ix_category": 1,
    "category": "Other Deductions",
    "ix_item": 1,
    "item": "AW CPF Contribution",
    "amount": 0
  },
  {
    "payroll_month": "2024-08-01T00:00:00.000Z",
    "adviser_id": 4,
    "adviser_full_name": "Lucie Hammond",
    "ix_section": 0,
    "section": "Gross Income",
    "ix_category": 0,
    "category": "Commission Income",
    "ix_item": 0,
    "item": "Gross Commission Income",
    "amount": 5239.15
  },
  {
    "payroll_month": "2024-08-01T00:00:00.000Z",
    "adviser_id": 4,
    "adviser_full_name": "Lucie Hammond",
    "ix_section": 0,
    "section": "Gross Income",
    "ix_category": 0,
    "category": "Commission Income",
    "ix_item": 1,
    "item": "GST",
    "amount": -432.5903669724774
  },
  {
    "payroll_month": "2024-08-01T00:00:00.000Z",
    "adviser_id": 4,
    "adviser_full_name": "Lucie Hammond",
    "ix_section": 0,
    "section": "Gross Income",
    "ix_category": 0,
    "category": "Commission Income",
    "ix_item": 2,
    "item": "Commission Income",
    "amount": 4806.559633027522
  },
  {
    "payroll_month": "2024-08-01T00:00:00.000Z",
    "adviser_id": 4,
    "adviser_full_name": "Lucie Hammond",
    "ix_section": 0,
    "section": "Gross Income",
    "ix_category": 1,
    "category": "Other Income",
    "ix_item": 0,
    "item": "Split Commission Income",
    "amount": 0
  },
  {
    "payroll_month": "2024-08-01T00:00:00.000Z",
    "adviser_id": 4,
    "adviser_full_name": "Lucie Hammond",
    "ix_section": 0,
    "section": "Gross Income",
    "ix_category": 2,
    "category": "Commission Expense",
    "ix_item": 0,
    "item": "TallRock Deduction",
    "amount": -1682.2958715596326
  },
  {
    "payroll_month": "2024-08-01T00:00:00.000Z",
    "adviser_id": 4,
    "adviser_full_name": "Lucie Hammond",
    "ix_section": 0,
    "section": "Gross Income",
    "ix_category": 2,
    "category": "Commission Expense",
    "ix_item": 1,
    "item": "15% Clawback",
    "amount": -139.62385321100916
  },
  {
    "payroll_month": "2024-08-01T00:00:00.000Z",
    "adviser_id": 4,
    "adviser_full_name": "Lucie Hammond",
    "ix_section": 0,
    "section": "Gross Income",
    "ix_category": 2,
    "category": "Commission Expense",
    "ix_item": 2,
    "item": "BDM Commission Expense",
    "amount": 0
  },
  {
    "payroll_month": "2024-09-01T00:00:00.000Z",
    "adviser_id": 4,
    "adviser_full_name": "Lucie Hammond",
    "ix_section": 0,
    "section": "Gross Income",
    "ix_category": 2,
    "category": "Commission Expense",
    "ix_item": 3,
    "item": "Chauffeur",
    "amount": 750
  },
  {
    "payroll_month": "2024-10-01T00:00:00.000Z",
    "adviser_id": 4,
    "adviser_full_name": "Lucie Hammond",
    "ix_section": 0,
    "section": "Gross Income",
    "ix_category": 2,
    "category": "Commission Expense",
    "ix_item": 4,
    "item": "Chauffeur",
    "amount": 750
  },
  {
    "payroll_month": "2024-11-01T00:00:00.000Z",
    "adviser_id": 4,
    "adviser_full_name": "Lucie Hammond",
    "ix_section": 0,
    "section": "Gross Income",
    "ix_category": 2,
    "category": "Commission Expense",
    "ix_item": 5,
    "item": "Chauffeur",
    "amount": 750
  },
  {
    "payroll_month": "2024-12-01T00:00:00.000Z",
    "adviser_id": 4,
    "adviser_full_name": "Lucie Hammond",
    "ix_section": 0,
    "section": "Gross Income",
    "ix_category": 2,
    "category": "Commission Expense",
    "ix_item": 6,
    "item": "Chauffeur",
    "amount": 750
  },
  {
    "payroll_month": "2024-08-01T00:00:00.000Z",
    "adviser_id": 4,
    "adviser_full_name": "Lucie Hammond",
    "ix_section": 1,
    "section": "Net Income",
    "ix_category": 1,
    "category": "Other Expenses",
    "ix_item": 0,
    "item": "Split Commission Expense",
    "amount": 0
  },
  {
    "payroll_month": "2024-08-01T00:00:00.000Z",
    "adviser_id": 4,
    "adviser_full_name": "Lucie Hammond",
    "ix_section": 2,
    "section": "Payment Amount",
    "ix_category": 0,
    "category": "Other Deductions",
    "ix_item": 0,
    "item": "OW CPF Contribution",
    "amount": 0
  },
  {
    "payroll_month": "2024-08-01T00:00:00.000Z",
    "adviser_id": 4,
    "adviser_full_name": "Lucie Hammond",
    "ix_section": 2,
    "section": "Payment Amount",
    "ix_category": 1,
    "category": "Other Deductions",
    "ix_item": 1,
    "item": "AW CPF Contribution",
    "amount": 0
  },
  {
    "payroll_month": "2024-08-01T00:00:00.000Z",
    "adviser_id": 14,
    "adviser_full_name": "Mark Beacher",
    "ix_section": 0,
    "section": "Gross Income",
    "ix_category": 0,
    "category": "Commission Income",
    "ix_item": 0,
    "item": "Gross Commission Income",
    "amount": 2244.0899999999997
  },
  {
    "payroll_month": "2024-08-01T00:00:00.000Z",
    "adviser_id": 14,
    "adviser_full_name": "Mark Beacher",
    "ix_section": 0,
    "section": "Gross Income",
    "ix_category": 0,
    "category": "Commission Income",
    "ix_item": 1,
    "item": "GST",
    "amount": -185.29183486238543
  },
  {
    "payroll_month": "2024-08-01T00:00:00.000Z",
    "adviser_id": 14,
    "adviser_full_name": "Mark Beacher",
    "ix_section": 0,
    "section": "Gross Income",
    "ix_category": 0,
    "category": "Commission Income",
    "ix_item": 2,
    "item": "Commission Income",
    "amount": 2058.7981651376144
  },
  {
    "payroll_month": "2024-08-01T00:00:00.000Z",
    "adviser_id": 14,
    "adviser_full_name": "Mark Beacher",
    "ix_section": 0,
    "section": "Gross Income",
    "ix_category": 1,
    "category": "Other Income",
    "ix_item": 0,
    "item": "Split Commission Income",
    "amount": 0
  },
  {
    "payroll_month": "2024-08-01T00:00:00.000Z",
    "adviser_id": 14,
    "adviser_full_name": "Mark Beacher",
    "ix_section": 0,
    "section": "Gross Income",
    "ix_category": 2,
    "category": "Commission Expense",
    "ix_item": 0,
    "item": "TallRock Deduction",
    "amount": -514.6995412844037
  },
  {
    "payroll_month": "2024-08-01T00:00:00.000Z",
    "adviser_id": 14,
    "adviser_full_name": "Mark Beacher",
    "ix_section": 0,
    "section": "Gross Income",
    "ix_category": 2,
    "category": "Commission Expense",
    "ix_item": 1,
    "item": "15% Clawback",
    "amount": -7.343119266055044
  },
  {
    "payroll_month": "2024-08-01T00:00:00.000Z",
    "adviser_id": 14,
    "adviser_full_name": "Mark Beacher",
    "ix_section": 0,
    "section": "Gross Income",
    "ix_category": 2,
    "category": "Commission Expense",
    "ix_item": 2,
    "item": "BDM Commission Expense",
    "amount": -8.811743119266055
  },
  {
    "payroll_month": "2024-08-01T00:00:00.000Z",
    "adviser_id": 14,
    "adviser_full_name": "Mark Beacher",
    "ix_section": 1,
    "section": "Net Income",
    "ix_category": 1,
    "category": "Other Expenses",
    "ix_item": 0,
    "item": "Split Commission Expense",
    "amount": 0
  },
  {
    "payroll_month": "2024-08-01T00:00:00.000Z",
    "adviser_id": 14,
    "adviser_full_name": "Mark Beacher",
    "ix_section": 2,
    "section": "Payment Amount",
    "ix_category": 0,
    "category": "Other Deductions",
    "ix_item": 0,
    "item": "OW CPF Contribution",
    "amount": 0
  },
  {
    "payroll_month": "2024-08-01T00:00:00.000Z",
    "adviser_id": 14,
    "adviser_full_name": "Mark Beacher",
    "ix_section": 2,
    "section": "Payment Amount",
    "ix_category": 1,
    "category": "Other Deductions",
    "ix_item": 1,
    "item": "AW CPF Contribution",
    "amount": 0
  },
  {
    "payroll_month": "2024-08-01T00:00:00.000Z",
    "adviser_id": 8,
    "adviser_full_name": "Rebecca Regan",
    "ix_section": 0,
    "section": "Gross Income",
    "ix_category": 0,
    "category": "Commission Income",
    "ix_item": 0,
    "item": "Gross Commission Income",
    "amount": 5414.08
  },
  {
    "payroll_month": "2024-08-01T00:00:00.000Z",
    "adviser_id": 8,
    "adviser_full_name": "Rebecca Regan",
    "ix_section": 0,
    "section": "Gross Income",
    "ix_category": 0,
    "category": "Commission Income",
    "ix_item": 1,
    "item": "GST",
    "amount": -447.0341284403675
  },
  {
    "payroll_month": "2024-08-01T00:00:00.000Z",
    "adviser_id": 8,
    "adviser_full_name": "Rebecca Regan",
    "ix_section": 0,
    "section": "Gross Income",
    "ix_category": 0,
    "category": "Commission Income",
    "ix_item": 2,
    "item": "Commission Income",
    "amount": 4967.045871559632
  },
  {
    "payroll_month": "2024-08-01T00:00:00.000Z",
    "adviser_id": 8,
    "adviser_full_name": "Rebecca Regan",
    "ix_section": 0,
    "section": "Gross Income",
    "ix_category": 1,
    "category": "Other Income",
    "ix_item": 0,
    "item": "Split Commission Income",
    "amount": 0
  },
  {
    "payroll_month": "2024-08-01T00:00:00.000Z",
    "adviser_id": 8,
    "adviser_full_name": "Rebecca Regan",
    "ix_section": 0,
    "section": "Gross Income",
    "ix_category": 2,
    "category": "Commission Expense",
    "ix_item": 0,
    "item": "TallRock Deduction",
    "amount": -993.4091743119262
  },
  {
    "payroll_month": "2024-08-01T00:00:00.000Z",
    "adviser_id": 8,
    "adviser_full_name": "Rebecca Regan",
    "ix_section": 0,
    "section": "Gross Income",
    "ix_category": 2,
    "category": "Commission Expense",
    "ix_item": 1,
    "item": "15% Clawback",
    "amount": -33.803669724770636
  },
  {
    "payroll_month": "2024-08-01T00:00:00.000Z",
    "adviser_id": 8,
    "adviser_full_name": "Rebecca Regan",
    "ix_section": 0,
    "section": "Gross Income",
    "ix_category": 2,
    "category": "Commission Expense",
    "ix_item": 2,
    "item": "BDM Commission Expense",
    "amount": 0
  },
  {
    "payroll_month": "2024-08-01T00:00:00.000Z",
    "adviser_id": 8,
    "adviser_full_name": "Rebecca Regan",
    "ix_section": 1,
    "section": "Net Income",
    "ix_category": 1,
    "category": "Other Expenses",
    "ix_item": 0,
    "item": "Split Commission Expense",
    "amount": 0
  },
  {
    "payroll_month": "2024-08-01T00:00:00.000Z",
    "adviser_id": 8,
    "adviser_full_name": "Rebecca Regan",
    "ix_section": 2,
    "section": "Payment Amount",
    "ix_category": 0,
    "category": "Other Deductions",
    "ix_item": 0,
    "item": "OW CPF Contribution",
    "amount": -167.03999999999996
  },
  {
    "payroll_month": "2024-08-01T00:00:00.000Z",
    "adviser_id": 8,
    "adviser_full_name": "Rebecca Regan",
    "ix_section": 2,
    "section": "Payment Amount",
    "ix_category": 1,
    "category": "Other Deductions",
    "ix_item": 1,
    "item": "AW CPF Contribution",
    "amount": 0
  },
  {
    "payroll_month": "2024-08-01T00:00:00.000Z",
    "adviser_id": 12,
    "adviser_full_name": "Robert Howland",
    "ix_section": 0,
    "section": "Gross Income",
    "ix_category": 0,
    "category": "Commission Income",
    "ix_item": 0,
    "item": "Gross Commission Income",
    "amount": 2416.15
  },
  {
    "payroll_month": "2024-08-01T00:00:00.000Z",
    "adviser_id": 12,
    "adviser_full_name": "Robert Howland",
    "ix_section": 0,
    "section": "Gross Income",
    "ix_category": 0,
    "category": "Commission Income",
    "ix_item": 1,
    "item": "GST",
    "amount": -199.49862385321123
  },
  {
    "payroll_month": "2024-08-01T00:00:00.000Z",
    "adviser_id": 12,
    "adviser_full_name": "Robert Howland",
    "ix_section": 0,
    "section": "Gross Income",
    "ix_category": 0,
    "category": "Commission Income",
    "ix_item": 2,
    "item": "Commission Income",
    "amount": 2216.651376146789
  },
  {
    "payroll_month": "2024-08-01T00:00:00.000Z",
    "adviser_id": 12,
    "adviser_full_name": "Robert Howland",
    "ix_section": 0,
    "section": "Gross Income",
    "ix_category": 1,
    "category": "Other Income",
    "ix_item": 0,
    "item": "Split Commission Income",
    "amount": 0
  },
  {
    "payroll_month": "2024-08-01T00:00:00.000Z",
    "adviser_id": 12,
    "adviser_full_name": "Robert Howland",
    "ix_section": 0,
    "section": "Gross Income",
    "ix_category": 2,
    "category": "Commission Expense",
    "ix_item": 0,
    "item": "TallRock Deduction",
    "amount": -554.1628440366972
  },
  {
    "payroll_month": "2024-08-01T00:00:00.000Z",
    "adviser_id": 12,
    "adviser_full_name": "Robert Howland",
    "ix_section": 0,
    "section": "Gross Income",
    "ix_category": 2,
    "category": "Commission Expense",
    "ix_item": 1,
    "item": "15% Clawback",
    "amount": -61.19999999999999
  },
  {
    "payroll_month": "2024-08-01T00:00:00.000Z",
    "adviser_id": 12,
    "adviser_full_name": "Robert Howland",
    "ix_section": 0,
    "section": "Gross Income",
    "ix_category": 2,
    "category": "Commission Expense",
    "ix_item": 2,
    "item": "BDM Commission Expense",
    "amount": 0
  },
  {
    "payroll_month": "2024-08-01T00:00:00.000Z",
    "adviser_id": 12,
    "adviser_full_name": "Robert Howland",
    "ix_section": 1,
    "section": "Net Income",
    "ix_category": 1,
    "category": "Other Expenses",
    "ix_item": 0,
    "item": "Split Commission Expense",
    "amount": 0
  },
  {
    "payroll_month": "2024-08-01T00:00:00.000Z",
    "adviser_id": 12,
    "adviser_full_name": "Robert Howland",
    "ix_section": 2,
    "section": "Payment Amount",
    "ix_category": 0,
    "category": "Other Deductions",
    "ix_item": 0,
    "item": "OW CPF Contribution",
    "amount": 0
  },
  {
    "payroll_month": "2024-08-01T00:00:00.000Z",
    "adviser_id": 12,
    "adviser_full_name": "Robert Howland",
    "ix_section": 2,
    "section": "Payment Amount",
    "ix_category": 1,
    "category": "Other Deductions",
    "ix_item": 1,
    "item": "AW CPF Contribution",
    "amount": 0
  },
  {
    "payroll_month": "2024-08-01T00:00:00.000Z",
    "adviser_id": 1,
    "adviser_full_name": "Shane Kepane",
    "ix_section": 0,
    "section": "Gross Income",
    "ix_category": 0,
    "category": "Commission Income",
    "ix_item": 0,
    "item": "Gross Commission Income",
    "amount": 50842.07999999999
  },
  {
    "payroll_month": "2024-08-01T00:00:00.000Z",
    "adviser_id": 1,
    "adviser_full_name": "Shane Kepane",
    "ix_section": 0,
    "section": "Gross Income",
    "ix_category": 0,
    "category": "Commission Income",
    "ix_item": 1,
    "item": "GST",
    "amount": -4197.969908256882
  },
  {
    "payroll_month": "2024-08-01T00:00:00.000Z",
    "adviser_id": 1,
    "adviser_full_name": "Shane Kepane",
    "ix_section": 0,
    "section": "Gross Income",
    "ix_category": 0,
    "category": "Commission Income",
    "ix_item": 2,
    "item": "Commission Income",
    "amount": 46644.1100917431
  },
  {
    "payroll_month": "2024-08-01T00:00:00.000Z",
    "adviser_id": 1,
    "adviser_full_name": "Shane Kepane",
    "ix_section": 0,
    "section": "Gross Income",
    "ix_category": 1,
    "category": "Other Income",
    "ix_item": 0,
    "item": "Split Commission Income",
    "amount": 0
  },
  {
    "payroll_month": "2024-08-01T00:00:00.000Z",
    "adviser_id": 1,
    "adviser_full_name": "Shane Kepane",
    "ix_section": 0,
    "section": "Gross Income",
    "ix_category": 2,
    "category": "Commission Expense",
    "ix_item": 0,
    "item": "TallRock Deduction",
    "amount": 0
  },
  {
    "payroll_month": "2024-08-01T00:00:00.000Z",
    "adviser_id": 1,
    "adviser_full_name": "Shane Kepane",
    "ix_section": 0,
    "section": "Gross Income",
    "ix_category": 2,
    "category": "Commission Expense",
    "ix_item": 1,
    "item": "15% Clawback",
    "amount": 0
  },
  {
    "payroll_month": "2024-08-01T00:00:00.000Z",
    "adviser_id": 1,
    "adviser_full_name": "Shane Kepane",
    "ix_section": 0,
    "section": "Gross Income",
    "ix_category": 2,
    "category": "Commission Expense",
    "ix_item": 2,
    "item": "BDM Commission Expense",
    "amount": 0
  },
  {
    "payroll_month": "2024-01-01T00:00:00.000Z",
    "adviser_id": 1,
    "adviser_full_name": "Shane Kepane",
    "ix_section": 0,
    "section": "Gross Income",
    "ix_category": 2,
    "category": "Commission Expense",
    "ix_item": 3,
    "item": "BDM Service",
    "amount": 175
  },
  {
    "payroll_month": "2024-02-01T00:00:00.000Z",
    "adviser_id": 1,
    "adviser_full_name": "Shane Kepane",
    "ix_section": 0,
    "section": "Gross Income",
    "ix_category": 2,
    "category": "Commission Expense",
    "ix_item": 4,
    "item": "BDM Service",
    "amount": 175
  },
  {
    "payroll_month": "2024-03-01T00:00:00.000Z",
    "adviser_id": 1,
    "adviser_full_name": "Shane Kepane",
    "ix_section": 0,
    "section": "Gross Income",
    "ix_category": 2,
    "category": "Commission Expense",
    "ix_item": 5,
    "item": "BDM Service",
    "amount": 175
  },
  {
    "payroll_month": "2024-04-01T00:00:00.000Z",
    "adviser_id": 1,
    "adviser_full_name": "Shane Kepane",
    "ix_section": 0,
    "section": "Gross Income",
    "ix_category": 2,
    "category": "Commission Expense",
    "ix_item": 6,
    "item": "BDM Service",
    "amount": 175
  },
  {
    "payroll_month": "2024-05-01T00:00:00.000Z",
    "adviser_id": 1,
    "adviser_full_name": "Shane Kepane",
    "ix_section": 0,
    "section": "Gross Income",
    "ix_category": 2,
    "category": "Commission Expense",
    "ix_item": 7,
    "item": "BDM Service",
    "amount": 175
  },
  {
    "payroll_month": "2024-06-01T00:00:00.000Z",
    "adviser_id": 1,
    "adviser_full_name": "Shane Kepane",
    "ix_section": 0,
    "section": "Gross Income",
    "ix_category": 2,
    "category": "Commission Expense",
    "ix_item": 8,
    "item": "BDM Service",
    "amount": 175
  },
  {
    "payroll_month": "2024-07-01T00:00:00.000Z",
    "adviser_id": 1,
    "adviser_full_name": "Shane Kepane",
    "ix_section": 0,
    "section": "Gross Income",
    "ix_category": 2,
    "category": "Commission Expense",
    "ix_item": 9,
    "item": "BDM Service",
    "amount": 175
  },
  {
    "payroll_month": "2024-08-01T00:00:00.000Z",
    "adviser_id": 1,
    "adviser_full_name": "Shane Kepane",
    "ix_section": 0,
    "section": "Gross Income",
    "ix_category": 2,
    "category": "Commission Expense",
    "ix_item": 10,
    "item": "BDM Service",
    "amount": 175
  },
  {
    "payroll_month": "2024-09-01T00:00:00.000Z",
    "adviser_id": 1,
    "adviser_full_name": "Shane Kepane",
    "ix_section": 0,
    "section": "Gross Income",
    "ix_category": 2,
    "category": "Commission Expense",
    "ix_item": 11,
    "item": "BDM Service",
    "amount": 175
  },
  {
    "payroll_month": "2024-10-01T00:00:00.000Z",
    "adviser_id": 1,
    "adviser_full_name": "Shane Kepane",
    "ix_section": 0,
    "section": "Gross Income",
    "ix_category": 2,
    "category": "Commission Expense",
    "ix_item": 12,
    "item": "BDM Service",
    "amount": 175
  },
  {
    "payroll_month": "2024-11-01T00:00:00.000Z",
    "adviser_id": 1,
    "adviser_full_name": "Shane Kepane",
    "ix_section": 0,
    "section": "Gross Income",
    "ix_category": 2,
    "category": "Commission Expense",
    "ix_item": 13,
    "item": "BDM Service",
    "amount": 175
  },
  {
    "payroll_month": "2024-12-01T00:00:00.000Z",
    "adviser_id": 1,
    "adviser_full_name": "Shane Kepane",
    "ix_section": 0,
    "section": "Gross Income",
    "ix_category": 2,
    "category": "Commission Expense",
    "ix_item": 14,
    "item": "BDM Service",
    "amount": 175
  },
  {
    "payroll_month": "2024-08-01T00:00:00.000Z",
    "adviser_id": 1,
    "adviser_full_name": "Shane Kepane",
    "ix_section": 1,
    "section": "Net Income",
    "ix_category": 0,
    "category": "Other Expenses",
    "ix_item": 2,
    "item": "Miscellaneous Expense",
    "amount": 2149.99
  },
  {
    "payroll_month": "2024-08-01T00:00:00.000Z",
    "adviser_id": 1,
    "adviser_full_name": "Shane Kepane",
    "ix_section": 1,
    "section": "Net Income",
    "ix_category": 1,
    "category": "Other Expenses",
    "ix_item": 0,
    "item": "Split Commission Expense",
    "amount": -64.74715596330276
  },
  {
    "payroll_month": "2024-08-01T00:00:00.000Z",
    "adviser_id": 1,
    "adviser_full_name": "Shane Kepane",
    "ix_section": 2,
    "section": "Payment Amount",
    "ix_category": 0,
    "category": "Other Deductions",
    "ix_item": 0,
    "item": "OW CPF Contribution",
    "amount": 0
  },
  {
    "payroll_month": "2024-08-01T00:00:00.000Z",
    "adviser_id": 1,
    "adviser_full_name": "Shane Kepane",
    "ix_section": 2,
    "section": "Payment Amount",
    "ix_category": 1,
    "category": "Other Deductions",
    "ix_item": 1,
    "item": "AW CPF Contribution",
    "amount": 0
  },
  {
    "payroll_month": "2024-08-01T00:00:00.000Z",
    "adviser_id": 15,
    "adviser_full_name": "Sufiyaan Zumla",
    "ix_section": 0,
    "section": "Gross Income",
    "ix_category": 0,
    "category": "Commission Income",
    "ix_item": 0,
    "item": "Gross Commission Income",
    "amount": 1.3399999999999999
  },
  {
    "payroll_month": "2024-08-01T00:00:00.000Z",
    "adviser_id": 15,
    "adviser_full_name": "Sufiyaan Zumla",
    "ix_section": 0,
    "section": "Gross Income",
    "ix_category": 0,
    "category": "Commission Income",
    "ix_item": 1,
    "item": "GST",
    "amount": -0.11064220183486247
  },
  {
    "payroll_month": "2024-08-01T00:00:00.000Z",
    "adviser_id": 15,
    "adviser_full_name": "Sufiyaan Zumla",
    "ix_section": 0,
    "section": "Gross Income",
    "ix_category": 0,
    "category": "Commission Income",
    "ix_item": 2,
    "item": "Commission Income",
    "amount": 1.2293577981651373
  },
  {
    "payroll_month": "2024-08-01T00:00:00.000Z",
    "adviser_id": 15,
    "adviser_full_name": "Sufiyaan Zumla",
    "ix_section": 0,
    "section": "Gross Income",
    "ix_category": 1,
    "category": "Other Income",
    "ix_item": 0,
    "item": "Split Commission Income",
    "amount": 0
  },
  {
    "payroll_month": "2024-08-01T00:00:00.000Z",
    "adviser_id": 15,
    "adviser_full_name": "Sufiyaan Zumla",
    "ix_section": 0,
    "section": "Gross Income",
    "ix_category": 2,
    "category": "Commission Expense",
    "ix_item": 0,
    "item": "TallRock Deduction",
    "amount": -0.27660550458715594
  },
  {
    "payroll_month": "2024-08-01T00:00:00.000Z",
    "adviser_id": 15,
    "adviser_full_name": "Sufiyaan Zumla",
    "ix_section": 0,
    "section": "Gross Income",
    "ix_category": 2,
    "category": "Commission Expense",
    "ix_item": 1,
    "item": "15% Clawback",
    "amount": 0
  },
  {
    "payroll_month": "2024-08-01T00:00:00.000Z",
    "adviser_id": 15,
    "adviser_full_name": "Sufiyaan Zumla",
    "ix_section": 0,
    "section": "Gross Income",
    "ix_category": 2,
    "category": "Commission Expense",
    "ix_item": 2,
    "item": "BDM Commission Expense",
    "amount": 0
  },
  {
    "payroll_month": "2024-08-01T00:00:00.000Z",
    "adviser_id": 15,
    "adviser_full_name": "Sufiyaan Zumla",
    "ix_section": 1,
    "section": "Net Income",
    "ix_category": 1,
    "category": "Other Expenses",
    "ix_item": 0,
    "item": "Split Commission Expense",
    "amount": 0
  },
  {
    "payroll_month": "2024-08-01T00:00:00.000Z",
    "adviser_id": 15,
    "adviser_full_name": "Sufiyaan Zumla",
    "ix_section": 2,
    "section": "Payment Amount",
    "ix_category": 0,
    "category": "Other Deductions",
    "ix_item": 0,
    "item": "OW CPF Contribution",
    "amount": 0
  },
  {
    "payroll_month": "2024-08-01T00:00:00.000Z",
    "adviser_id": 15,
    "adviser_full_name": "Sufiyaan Zumla",
    "ix_section": 2,
    "section": "Payment Amount",
    "ix_category": 1,
    "category": "Other Deductions",
    "ix_item": 1,
    "item": "AW CPF Contribution",
    "amount": 0
  },
  {
    "payroll_month": "2024-08-01T00:00:00.000Z",
    "adviser_id": 11,
    "adviser_full_name": "Tanya Maher",
    "ix_section": 0,
    "section": "Gross Income",
    "ix_category": 0,
    "category": "Commission Income",
    "ix_item": 0,
    "item": "Gross Commission Income",
    "amount": 2161.92
  },
  {
    "payroll_month": "2024-08-01T00:00:00.000Z",
    "adviser_id": 11,
    "adviser_full_name": "Tanya Maher",
    "ix_section": 0,
    "section": "Gross Income",
    "ix_category": 0,
    "category": "Commission Income",
    "ix_item": 1,
    "item": "GST",
    "amount": -178.50715596330292
  },
  {
    "payroll_month": "2024-08-01T00:00:00.000Z",
    "adviser_id": 11,
    "adviser_full_name": "Tanya Maher",
    "ix_section": 0,
    "section": "Gross Income",
    "ix_category": 0,
    "category": "Commission Income",
    "ix_item": 2,
    "item": "Commission Income",
    "amount": 1983.4128440366972
  },
  {
    "payroll_month": "2024-08-01T00:00:00.000Z",
    "adviser_id": 11,
    "adviser_full_name": "Tanya Maher",
    "ix_section": 0,
    "section": "Gross Income",
    "ix_category": 1,
    "category": "Other Income",
    "ix_item": 0,
    "item": "Split Commission Income",
    "amount": 0
  },
  {
    "payroll_month": "2024-08-01T00:00:00.000Z",
    "adviser_id": 11,
    "adviser_full_name": "Tanya Maher",
    "ix_section": 0,
    "section": "Gross Income",
    "ix_category": 2,
    "category": "Commission Expense",
    "ix_item": 0,
    "item": "TallRock Deduction",
    "amount": -446.2678899082568
  },
  {
    "payroll_month": "2024-08-01T00:00:00.000Z",
    "adviser_id": 11,
    "adviser_full_name": "Tanya Maher",
    "ix_section": 0,
    "section": "Gross Income",
    "ix_category": 2,
    "category": "Commission Expense",
    "ix_item": 1,
    "item": "15% Clawback",
    "amount": 0
  },
  {
    "payroll_month": "2024-08-01T00:00:00.000Z",
    "adviser_id": 11,
    "adviser_full_name": "Tanya Maher",
    "ix_section": 0,
    "section": "Gross Income",
    "ix_category": 2,
    "category": "Commission Expense",
    "ix_item": 2,
    "item": "BDM Commission Expense",
    "amount": 0
  },
  {
    "payroll_month": "2024-08-01T00:00:00.000Z",
    "adviser_id": 11,
    "adviser_full_name": "Tanya Maher",
    "ix_section": 1,
    "section": "Net Income",
    "ix_category": 1,
    "category": "Other Expenses",
    "ix_item": 0,
    "item": "Split Commission Expense",
    "amount": 0
  },
  {
    "payroll_month": "2024-08-01T00:00:00.000Z",
    "adviser_id": 11,
    "adviser_full_name": "Tanya Maher",
    "ix_section": 2,
    "section": "Payment Amount",
    "ix_category": 0,
    "category": "Other Deductions",
    "ix_item": 0,
    "item": "OW CPF Contribution",
    "amount": -59.5023853211009
  },
  {
    "payroll_month": "2024-08-01T00:00:00.000Z",
    "adviser_id": 11,
    "adviser_full_name": "Tanya Maher",
    "ix_section": 2,
    "section": "Payment Amount",
    "ix_category": 1,
    "category": "Other Deductions",
    "ix_item": 1,
    "item": "AW CPF Contribution",
    "amount": 0
  }
]